README.md
setup.py
ds_tomato.egg-info/PKG-INFO
ds_tomato.egg-info/SOURCES.txt
ds_tomato.egg-info/dependency_links.txt
ds_tomato.egg-info/requires.txt
ds_tomato.egg-info/top_level.txt
dstoamto/__init__.py
dstoamto/ds_tomato.py