Metadata-Version: 2.1
Name: ds_tomato
Version: 1.1
Requires-Dist: openai
Requires-Dist: langchain
Requires-Dist: langchain-openai
Requires-Dist: pinecone-client
Requires-Dist: langchain-community
Requires-Dist: langchain-pinecone
